computer2mqtt/__init__.py
computer2mqtt-0.1.2.dist-info/METADATA
computer2mqtt-0.1.2.dist-info/WHEEL
computer2mqtt-0.1.2.dist-info/entry_points.txt
computer2mqtt-0.1.2.dist-info/RECORD
