Metadata-Version: 2.3
Name: computer2mqtt
Version: 0.1.2
Summary: This project is a multi-system and multi-OS adaptation of mac2mqtt. It allows you to execute any command on your system, providing endless possibilities for automation and control.
Requires-Python: >=3.12
Requires-Dist: aiomqtt>=2.3.0
Requires-Dist: click>=8.1.7
Requires-Dist: pyyaml>=6.0.2
Provides-Extra: dev
Requires-Dist: pre-commit>=3.3.3; extra == 'dev'
Requires-Dist: pytest; extra == 'dev'
Requires-Dist: pytest-asyncio<0.23; extra == 'dev'
Requires-Dist: pytest-cov; extra == 'dev'
Requires-Dist: ruff>=0.6.3; extra == 'dev'
Provides-Extra: release
Requires-Dist: twine; extra == 'release'
